{
  "extracted": "2025-07-30T20:53:15.019Z",
  "sources": [
    "https://www.pineinktattoos.com/",
    "https://www.pineinktattoos.com/about-1",
    "https://www.pineinktattoos.com/copy-of-about"
  ],
  "categories": {
    "work": "tattoo photos, healed tattoos, portfolio pieces",
    "artists": "artist photos, headshots, team pictures",
    "shop": "interior photos, exterior shots, studio images",
    "branding": "logos, signs, brand elements"
  },
  "images": {
    "work": [],
    "artists": [],
    "shop": [],
    "branding": []
  }
}